.gitignore
LICENSE.txt
MODEL_CARD.md
README.md
setup.cfg
setup.py
asset/api.gif
asset/api.png
asset/diagram.png
asset/summary/summary_in_domain.csv
asset/summary/summary_in_domain.panx.csv
asset/summary/summary_out_domain_es_f1.csv
asset/summary/summary_out_domain_es_f1.lower.csv
asset/summary/summary_out_domain_es_f1.panx.csv
asset/summary/summary_out_domain_es_precision.csv
asset/summary/summary_out_domain_es_precision.lower.csv
asset/summary/summary_out_domain_es_precision.panx.csv
asset/summary/summary_out_domain_es_recall.csv
asset/summary/summary_out_domain_es_recall.lower.csv
asset/summary/summary_out_domain_es_recall.panx.csv
asset/summary/summary_out_domain_ner_f1.csv
asset/summary/summary_out_domain_ner_f1.lower.csv
asset/summary/summary_out_domain_ner_f1.panx.csv
asset/summary/summary_out_domain_ner_precision.csv
asset/summary/summary_out_domain_ner_precision.lower.csv
asset/summary/summary_out_domain_ner_precision.panx.csv
asset/summary/summary_out_domain_ner_recall.csv
asset/summary/summary_out_domain_ner_recall.lower.csv
asset/summary/summary_out_domain_ner_recall.panx.csv
static/css/app.css
static/css/bootstrap.css.map
static/css/bootstrap.min.css
static/js/app.js
static/js/bootstrap.min.js
static/js/jquery-3.4.1.min.js
templates/index.html
tests/test_data.py
tner/__init__.py
tner/get_dataset.py
tner/ner_model.py
tner/ner_tokenizer.py
tner/ner_trainer.py
tner/tokenizer_ja.py
tner/util.py
tner.egg-info/PKG-INFO
tner.egg-info/SOURCES.txt
tner.egg-info/dependency_links.txt
tner.egg-info/entry_points.txt
tner.egg-info/requires.txt
tner.egg-info/top_level.txt
tner/tner_cl/__init__.py
tner/tner_cl/evaluate.py
tner/tner_cl/predict.py
tner/tner_cl/push_to_hub.py
tner/tner_cl/readme_template.py
tner/tner_cl/train.py