Metadata-Version: 2.1
Name: tner
Version: 0.2.1
Summary: Transformer-based named entity recognition
Home-page: https://github.com/asahi417/tner
Author: Asahi Ushio
Author-email: asahi1992ushio@gmail.com
License: MIT
Download-URL: https://github.com/asahi417/tner/archive/0.2.1.tar.gz
Keywords: ner,nlp,language-model
Platform: UNKNOWN
Classifier: Development Status :: 4 - Beta
Classifier: Intended Audience :: Developers
Classifier: Intended Audience :: Science/Research
Classifier: Topic :: Scientific/Engineering
Classifier: License :: OSI Approved :: MIT License
Classifier: Programming Language :: Python :: 3
Requires-Python: >=3.6
Provides-Extra: app
Provides-Extra: japanese
License-File: LICENSE.txt
